cpc.mpp-0.3.1-py3.7-nspkg.pth
cpc/mpp/__init__.py
cpc/mpp/bc.py
cpc/mpp/cal.py
cpc/mpp/plot_poe_charts.py
tests/__init__.py
tests/test_main.py
cpc.mpp-0.3.1.dist-info/AUTHORS.md
cpc.mpp-0.3.1.dist-info/LICENSE.md
cpc.mpp-0.3.1.dist-info/METADATA
cpc.mpp-0.3.1.dist-info/WHEEL
cpc.mpp-0.3.1.dist-info/namespace_packages.txt
cpc.mpp-0.3.1.dist-info/top_level.txt
cpc.mpp-0.3.1.dist-info/RECORD
