Metadata-Version: 2.1
Name: cpc.mpp
Version: 0.3.1
Summary: Model post processing package
Home-page: https://github.com/mikecharles/cpc.mpp
Author: Mike Charles
Author-email: mike.charles@noaa.gov
License: CC
Platform: UNKNOWN
Classifier: Development Status :: 1 - Planning
Classifier: Environment :: Console
Classifier: Intended Audience :: Science/Research
Classifier: Programming Language :: Python
Classifier: Programming Language :: Python :: 3
Classifier: Operating System :: OS Independent
Classifier: Topic :: Scientific/Engineering :: Atmospheric Science
Classifier: License :: CC0 1.0 Universal (CC0 1.0) Public Domain Dedication
Requires-Dist: scipy
Requires-Dist: numpy
Requires-Dist: cpc.geofiles
Requires-Dist: cpc.stats
